grisera/__init__.py
grisera/activity/__init__.py
grisera/activity/activity_model.py
grisera/activity/activity_router.py
grisera/activity/activity_service.py
grisera/activity_execution/__init__.py
grisera/activity_execution/activity_execution_model.py
grisera/activity_execution/activity_execution_router.py
grisera/activity_execution/activity_execution_service.py
grisera/appearance/__init__.py
grisera/appearance/appearance_model.py
grisera/appearance/appearance_router.py
grisera/appearance/appearance_service.py
grisera/arrangement/__init__.py
grisera/arrangement/arrangement_model.py
grisera/arrangement/arrangement_router.py
grisera/arrangement/arrangement_service.py
grisera/auth/__init__.py
grisera/auth/auth_bearer.py
grisera/auth/auth_config.py
grisera/auth/auth_handler.py
grisera/auth/auth_module.py
grisera/channel/__init__.py
grisera/channel/channel_model.py
grisera/channel/channel_router.py
grisera/channel/channel_service.py
grisera/dataset/__init__.py
grisera/dataset/dataset_model.py
grisera/dataset/dataset_router.py
grisera/dataset/dataset_service.py
grisera/experiment/__init__.py
grisera/experiment/experiment_model.py
grisera/experiment/experiment_router.py
grisera/experiment/experiment_service.py
grisera/helpers/__init__.py
grisera/helpers/hateoas.py
grisera/helpers/helpers.py
grisera/life_activity/__init__.py
grisera/life_activity/life_activity_model.py
grisera/life_activity/life_activity_router.py
grisera/life_activity/life_activity_service.py
grisera/measure/__init__.py
grisera/measure/measure_model.py
grisera/measure/measure_router.py
grisera/measure/measure_service.py
grisera/measure_name/__init__.py
grisera/measure_name/measure_name_model.py
grisera/measure_name/measure_name_router.py
grisera/measure_name/measure_name_service.py
grisera/modality/__init__.py
grisera/modality/modality_model.py
grisera/modality/modality_router.py
grisera/modality/modality_service.py
grisera/models/__init__.py
grisera/models/base_model_out.py
grisera2-0.0.39.6.dist-info/LICENSE
grisera2-0.0.39.6.dist-info/METADATA
grisera2-0.0.39.6.dist-info/WHEEL
grisera2-0.0.39.6.dist-info/top_level.txt
grisera2-0.0.39.6.dist-info/RECORD
